markitdown1/__init__.py
markitdown1/cli.py
markitdown1/core.py
markitdown1/getmd1.py
markitdown1/merge_mds.py
markitdown1-0.1.1.dist-info/METADATA
markitdown1-0.1.1.dist-info/WHEEL
markitdown1-0.1.1.dist-info/entry_points.txt
markitdown1-0.1.1.dist-info/top_level.txt
markitdown1-0.1.1.dist-info/RECORD
