Metadata-Version: 2.4
Name: markitdown1
Version: 0.1.1
Summary: Batch convert documents to Markdown using MarkItDown
Requires-Python: >=3.8
Requires-Dist: markitdown
Requires-Dist: requests
Requires-Dist: argparse
Provides-Extra: all
Requires-Dist: markitdown[all]; extra == "all"
